samplemongoconnect/__init__.py
samplemongoconnect/mongo_crud.py
samplemongoconnect-0.0.4.dist-info/METADATA
samplemongoconnect-0.0.4.dist-info/WHEEL
samplemongoconnect-0.0.4.dist-info/top_level.txt
samplemongoconnect-0.0.4.dist-info/RECORD
